{
    "MI": {
        "register_day": 9,
        "absentee_year": 2018,
        "register_year": 2018,
        "election_month": 8,
        "election_day": 7,
        "election_year": 2018,
        "absentee_day": 4,
        "register_month": 7,
        "election_names": [
            "Michigan State Primary Election"
        ],
        "absentee_month": 8
    },
    "KY": {
        "register_day": 23,
        "absentee_year": 2018,
        "register_year": 2018,
        "election_month": 5,
        "election_day": 22,
        "election_year": 2018,
        "absentee_day": 15,
        "register_month": 4,
        "election_names": [
            "Kentucky State Primary Election"
        ],
        "absentee_month": 5
    },
    "MO": {
        "register_day": 11,
        "absentee_year": 2018,
        "register_year": 2018,
        "election_month": 8,
        "election_day": 7,
        "election_year": 2018,
        "absentee_day": 1,
        "register_month": 7,
        "election_names": [
            "Missouri State Primary Election"
        ],
        "absentee_month": 8
    },
    "WY": {
        "register_day": 6,
        "absentee_year": 2018,
        "register_year": 2018,
        "election_month": 8,
        "election_day": 21,
        "election_year": 2018,
        "absentee_day": 20,
        "register_month": 8,
        "election_names": [
            "Wyoming State Primary Election"
        ],
        "absentee_month": 8
    },
    "DE": {
        "register_day": 11,
        "absentee_year": 2018,
        "register_year": 2018,
        "election_month": 9,
        "election_day": 6,
        "election_year": 2018,
        "absentee_day": 4,
        "register_month": 8,
        "election_names": [
            "Delaware Primary Election"
        ],
        "absentee_month": 9
    },
    "MS": {
        "register_day": 7,
        "absentee_year": -1,
        "register_year": 2018,
        "election_month": 6,
        "election_day": 5,
        "election_year": 2018,
        "absentee_day": -1,
        "register_month": 5,
        "election_names": [
            "Mississippi Primary Election"
        ],
        "absentee_month": -1
    },
    "IL": {
        "register_day": 20,
        "absentee_year": 2018,
        "register_year": 2018,
        "election_month": 3,
        "election_day": 20,
        "election_year": 2018,
        "absentee_day": 15,
        "register_month": 2,
        "election_names": [
            "Illinois State Primary Election"
        ],
        "absentee_month": 3
    },
    "FL": {
        "register_day": 16,
        "absentee_year": 2018,
        "register_year": 2018,
        "election_month": 2,
        "election_day": 13,
        "election_year": 2018,
        "absentee_day": 7,
        "register_month": 1,
        "election_names": [
            "State House District 72 Special General Election"
        ],
        "absentee_month": 2
    },
    "NJ": {
        "register_day": 15,
        "absentee_year": 2018,
        "register_year": 2018,
        "election_month": 6,
        "election_day": 5,
        "election_year": 2018,
        "absentee_day": 29,
        "register_month": 5,
        "election_names": [
            "New Jersey Primary Election"
        ],
        "absentee_month": 5
    },
    "MN": {
        "register_day": 24,
        "absentee_year": 2018,
        "register_year": 2018,
        "election_month": 8,
        "election_day": 14,
        "election_year": 2018,
        "absentee_day": 14,
        "register_month": 7,
        "election_names": [
            "Minnesota State Primary Election"
        ],
        "absentee_month": 8
    },
    "IA": {
        "register_day": 25,
        "absentee_year": 2018,
        "register_year": 2018,
        "election_month": 6,
        "election_day": 5,
        "election_year": 2018,
        "absentee_day": 25,
        "register_month": 5,
        "election_names": [
            "Iowa Primary Election"
        ],
        "absentee_month": 5
    },
    "NE": {
        "register_day": 30,
        "absentee_year": 2018,
        "register_year": 2018,
        "election_month": 5,
        "election_day": 15,
        "election_year": 2018,
        "absentee_day": 4,
        "register_month": 4,
        "election_names": [
            "Nebraska State Primary Election"
        ],
        "absentee_month": 5
    },
    "UT": {
        "register_day": 28,
        "absentee_year": 2018,
        "register_year": 2018,
        "election_month": 6,
        "election_day": 26,
        "election_year": 2018,
        "absentee_day": 21,
        "register_month": 5,
        "election_names": [
            "Utah Primary Election"
        ],
        "absentee_month": 6
    },
    "MD": {
        "register_day": 5,
        "absentee_year": 2018,
        "register_year": 2018,
        "election_month": 6,
        "election_day": 26,
        "election_year": 2018,
        "absentee_day": 19,
        "register_month": 6,
        "election_names": [
            "Maryland Primary Election"
        ],
        "absentee_month": 6
    },
    "AS": {
        "register_day": 9,
        "absentee_year": 2018,
        "register_year": 2018,
        "election_month": 11,
        "election_day": 6,
        "election_year": 2018,
        "absentee_day": 5,
        "register_month": 10,
        "election_names": [
            "American Samoa General Election"
        ],
        "absentee_month": 11
    },
    "KS": {
        "register_day": 17,
        "absentee_year": 2018,
        "register_year": 2018,
        "election_month": 8,
        "election_day": 7,
        "election_year": 2018,
        "absentee_day": 3,
        "register_month": 7,
        "election_names": [
            "Kansas State Primary Election"
        ],
        "absentee_month": 8
    },
    "CA": {
        "register_day": 21,
        "absentee_year": 2018,
        "register_year": 2018,
        "election_month": 6,
        "election_day": 5,
        "election_year": 2018,
        "absentee_day": 29,
        "register_month": 5,
        "election_names": [
            "California Statewide Direct Primary Election"
        ],
        "absentee_month": 5
    },
    "OR": {
        "register_day": 24,
        "absentee_year": 2018,
        "register_year": 2018,
        "election_month": 5,
        "election_day": 15,
        "election_year": 2018,
        "absentee_day": 10,
        "register_month": 4,
        "election_names": [
            "Oregon State Primary Election"
        ],
        "absentee_month": 5
    },
    "SC": {
        "register_day": -1,
        "absentee_year": 2018,
        "register_year": -1,
        "election_month": 1,
        "election_day": 16,
        "election_year": 2018,
        "absentee_day": 12,
        "register_month": -1,
        "election_names": [
            "State House of Representatives District 99 Special General Election",
            "State House of Representatives District 28 Special General Election"
        ],
        "absentee_month": 1
    },
    "NY": {
        "register_day": 17,
        "absentee_year": 2018,
        "register_year": 2018,
        "election_month": 9,
        "election_day": 11,
        "election_year": 2018,
        "absentee_day": 4,
        "register_month": 8,
        "election_names": [
            "New York Primary Election"
        ],
        "absentee_month": 9
    },
    "MA": {
        "register_day": 29,
        "absentee_year": 2018,
        "register_year": 2018,
        "election_month": 9,
        "election_day": 18,
        "election_year": 2018,
        "absentee_day": 17,
        "register_month": 8,
        "election_names": [
            "Massachusetts Primary Election"
        ],
        "absentee_month": 9
    },
    "HI": {
        "register_day": 12,
        "absentee_year": 2018,
        "register_year": 2018,
        "election_month": 8,
        "election_day": 11,
        "election_year": 2018,
        "absentee_day": 4,
        "register_month": 7,
        "election_names": [
            "Hawaii State Primary Election"
        ],
        "absentee_month": 8
    },
    "TN": {
        "register_day": 3,
        "absentee_year": 2018,
        "register_year": 2018,
        "election_month": 8,
        "election_day": 2,
        "election_year": 2018,
        "absentee_day": 26,
        "register_month": 7,
        "election_names": [
            "Tennessee State Primary Election"
        ],
        "absentee_month": 7
    },
    "ME": {
        "register_day": 22,
        "absentee_year": 2018,
        "register_year": 2018,
        "election_month": 6,
        "election_day": 12,
        "election_year": 2018,
        "absentee_day": 7,
        "register_month": 5,
        "election_names": [
            "Maine Primary Election"
        ],
        "absentee_month": 6
    },
    "IN": {
        "register_day": 9,
        "absentee_year": 2018,
        "register_year": 2018,
        "election_month": 5,
        "election_day": 8,
        "election_year": 2018,
        "absentee_day": 30,
        "register_month": 4,
        "election_names": [
            "Indiana State Primary Election"
        ],
        "absentee_month": 4
    },
    "AZ": {
        "register_day": 30,
        "absentee_year": 2018,
        "register_year": 2018,
        "election_month": 8,
        "election_day": 28,
        "election_year": 2018,
        "absentee_day": 17,
        "register_month": 7,
        "election_names": [
            "Arizona State Primary Election"
        ],
        "absentee_month": 8
    },
    "NV": {
        "register_day": 15,
        "absentee_year": 2018,
        "register_year": 2018,
        "election_month": 6,
        "election_day": 12,
        "election_year": 2018,
        "absentee_day": 5,
        "register_month": 5,
        "election_names": [
            "Nevada Primary Election"
        ],
        "absentee_month": 6
    },
    "AR": {
        "register_day": 23,
        "absentee_year": 2018,
        "register_year": 2018,
        "election_month": 5,
        "election_day": 22,
        "election_year": 2018,
        "absentee_day": 15,
        "register_month": 4,
        "election_names": [
            "Arkansas State Primary Election"
        ],
        "absentee_month": 5
    },
    "VI": {
        "register_day": 5,
        "absentee_year": -1,
        "register_year": 2018,
        "election_month": 11,
        "election_day": 6,
        "election_year": 2018,
        "absentee_day": -1,
        "register_month": 10,
        "election_names": [
            "Virgin Islands General Election"
        ],
        "absentee_month": -1
    },
    "VA": {
        "register_day": 21,
        "absentee_year": 2018,
        "register_year": 2018,
        "election_month": 6,
        "election_day": 12,
        "election_year": 2018,
        "absentee_day": 5,
        "register_month": 5,
        "election_names": [
            "Virginia Primary Election"
        ],
        "absentee_month": 6
    },
    "RI": {
        "register_day": 12,
        "absentee_year": 2018,
        "register_year": 2018,
        "election_month": 9,
        "election_day": 12,
        "election_year": 2018,
        "absentee_day": 21,
        "register_month": 8,
        "election_names": [
            "Rhode Island Primary Election"
        ],
        "absentee_month": 8
    },
    "SD": {
        "register_day": 21,
        "absentee_year": 2018,
        "register_year": 2018,
        "election_month": 6,
        "election_day": 5,
        "election_year": 2018,
        "absentee_day": 4,
        "register_month": 5,
        "election_names": [
            "South Dakota Primary Election"
        ],
        "absentee_month": 6
    },
    "GA": {
        "register_day": 23,
        "absentee_year": 2018,
        "register_year": 2018,
        "election_month": 5,
        "election_day": 22,
        "election_year": 2018,
        "absentee_day": 18,
        "register_month": 4,
        "election_names": [
            "Georgia State Primary Election"
        ],
        "absentee_month": 5
    },
    "CT": {
        "register_day": 24,
        "absentee_year": 2018,
        "register_year": 2018,
        "election_month": 8,
        "election_day": 14,
        "election_year": 2018,
        "absentee_day": 13,
        "register_month": 7,
        "election_names": [
            "Connecticut State Primary Election"
        ],
        "absentee_month": 8
    },
    "OK": {
        "register_day": 8,
        "absentee_year": 2018,
        "register_year": 2018,
        "election_month": 6,
        "election_day": 26,
        "election_year": 2018,
        "absentee_day": 20,
        "register_month": 6,
        "election_names": [
            "Oklahoma Primary Election"
        ],
        "absentee_month": 6
    },
    "PA": {
        "register_day": 16,
        "absentee_year": 2018,
        "register_year": 2018,
        "election_month": 5,
        "election_day": 15,
        "election_year": 2018,
        "absentee_day": 8,
        "register_month": 4,
        "election_names": [
            "Pennsylvania State Primary Election"
        ],
        "absentee_month": 5
    },
    "NC": {
        "register_day": 13,
        "absentee_year": 2018,
        "register_year": 2018,
        "election_month": 5,
        "election_day": 8,
        "election_year": 2018,
        "absentee_day": 1,
        "register_month": 4,
        "election_names": [
            "North Carolina State Primary Election"
        ],
        "absentee_month": 5
    },
    "WI": {
        "register_day": 25,
        "absentee_year": 2018,
        "register_year": 2018,
        "election_month": 8,
        "election_day": 14,
        "election_year": 2018,
        "absentee_day": 9,
        "register_month": 7,
        "election_names": [
            "Wisconsin State Primary Election"
        ],
        "absentee_month": 8
    },
    "DC": {
        "register_day": 28,
        "absentee_year": 2018,
        "register_year": 2018,
        "election_month": 6,
        "election_day": 19,
        "election_year": 2018,
        "absentee_day": 16,
        "register_month": 5,
        "election_names": [
            "District of Columbia Primary Election"
        ],
        "absentee_month": 6
    },
    "VT": {
        "register_day": 14,
        "absentee_year": 2018,
        "register_year": 2018,
        "election_month": 8,
        "election_day": 14,
        "election_year": 2018,
        "absentee_day": 13,
        "register_month": 8,
        "election_names": [
            "Vermont State Primary Election"
        ],
        "absentee_month": 8
    },
    "WA": {
        "register_day": 9,
        "absentee_year": 2018,
        "register_year": 2018,
        "election_month": 8,
        "election_day": 7,
        "election_year": 2018,
        "absentee_day": 9,
        "register_month": 7,
        "election_names": [
            "Washington State Primary Election"
        ],
        "absentee_month": 7
    },
    "CO": {
        "register_day": 18,
        "absentee_year": -1,
        "register_year": 2018,
        "election_month": 6,
        "election_day": 26,
        "election_year": 2018,
        "absentee_day": -1,
        "register_month": 6,
        "election_names": [
            "Colorado Primary Election"
        ],
        "absentee_month": -1
    },
    "MT": {
        "register_day": 7,
        "absentee_year": 2018,
        "register_year": 2018,
        "election_month": 6,
        "election_day": 5,
        "election_year": 2018,
        "absentee_day": 4,
        "register_month": 5,
        "election_names": [
            "Montana Primary Election"
        ],
        "absentee_month": 6
    },
    "WV": {
        "register_day": 17,
        "absentee_year": 2018,
        "register_year": 2018,
        "election_month": 5,
        "election_day": 8,
        "election_year": 2018,
        "absentee_day": 2,
        "register_month": 4,
        "election_names": [
            "West Virginia State Primary Election"
        ],
        "absentee_month": 5
    },
    "LA": {
        "register_day": 9,
        "absentee_year": 2018,
        "register_year": 2018,
        "election_month": 11,
        "election_day": 6,
        "election_year": 2018,
        "absentee_day": 2,
        "register_month": 10,
        "election_names": [
            "Louisiana State Primary Election"
        ],
        "absentee_month": 11
    },
    "MP": {
        "register_day": 7,
        "absentee_year": 2018,
        "register_year": 2018,
        "election_month": 11,
        "election_day": 6,
        "election_year": 2018,
        "absentee_day": 12,
        "register_month": 9,
        "election_names": [
            "Northern Mariana Islands General Election"
        ],
        "absentee_month": 10
    },
    "GU": {
        "register_day": 15,
        "absentee_year": 2018,
        "register_year": 2018,
        "election_month": 8,
        "election_day": 25,
        "election_year": 2018,
        "absentee_day": 22,
        "register_month": 8,
        "election_names": [
            "Guam Territory Primary Election"
        ],
        "absentee_month": 8
    },
    "TX": {
        "register_day": 5,
        "absentee_year": 2018,
        "register_year": 2018,
        "election_month": 3,
        "election_day": 6,
        "election_year": 2018,
        "absentee_day": 23,
        "register_month": 2,
        "election_names": [
            "Texas State Primary Election"
        ],
        "absentee_month": 2
    },
    "AK": {
        "register_day": 22,
        "absentee_year": 2018,
        "register_year": 2018,
        "election_month": 8,
        "election_day": 21,
        "election_year": 2018,
        "absentee_day": 11,
        "register_month": 7,
        "election_names": [
            "Alaska State Primary Election"
        ],
        "absentee_month": 8
    },
    "OH": {
        "register_day": 9,
        "absentee_year": 2018,
        "register_year": 2018,
        "election_month": 5,
        "election_day": 8,
        "election_year": 2018,
        "absentee_day": 5,
        "register_month": 4,
        "election_names": [
            "Ohio State Primary Election"
        ],
        "absentee_month": 5
    },
    "AL": {
        "register_day": 12,
        "absentee_year": 2018,
        "register_year": 2018,
        "election_month": 3,
        "election_day": 27,
        "election_year": 2018,
        "absentee_day": 22,
        "register_month": 3,
        "election_names": [
            "State House District 21 Special General Election"
        ],
        "absentee_month": 3
    },
    "ID": {
        "register_day": 20,
        "absentee_year": 2018,
        "register_year": 2018,
        "election_month": 5,
        "election_day": 15,
        "election_year": 2018,
        "absentee_day": 4,
        "register_month": 4,
        "election_names": [
            "Idaho Primary Election"
        ],
        "absentee_month": 5
    },
    "ND": {
        "register_day": -1,
        "absentee_year": 2018,
        "register_year": -1,
        "election_month": 6,
        "election_day": 12,
        "election_year": 2018,
        "absentee_day": 11,
        "register_month": -1,
        "election_names": [
            "North Dakota Primary Election"
        ],
        "absentee_month": 6
    },
    "NH": {
        "register_day": 11,
        "absentee_year": 2018,
        "register_year": 2018,
        "election_month": 9,
        "election_day": 11,
        "election_year": 2018,
        "absentee_day": 10,
        "register_month": 9,
        "election_names": [
            "New Hampshire Primary Election"
        ],
        "absentee_month": 9
    },
    "NM": {
        "register_day": 8,
        "absentee_year": 2018,
        "register_year": 2018,
        "election_month": 6,
        "election_day": 5,
        "election_year": 2018,
        "absentee_day": 1,
        "register_month": 5,
        "election_names": [
            "New Mexico Primary Election"
        ],
        "absentee_month": 6
    }
}